hidden_selenium/__init__.py
hidden_selenium/browser.py
hidden_selenium-0.1.2.dist-info/licenses/LICENSE
hidden_selenium-0.1.2.dist-info/METADATA
hidden_selenium-0.1.2.dist-info/WHEEL
hidden_selenium-0.1.2.dist-info/top_level.txt
hidden_selenium-0.1.2.dist-info/RECORD
