Metadata-Version: 2.4
Name: hidden_selenium
Version: 0.1.2
Summary: A stealthy undetected browser automation tool using Selenium.
Author: Max Base
Requires-Python: >=3.7
License-File: LICENSE
Requires-Dist: undetected-chromedriver>=3.5.3
Dynamic: author
Dynamic: description
Dynamic: description-content-type
Dynamic: license-file
Dynamic: requires-dist
Dynamic: requires-python
Dynamic: summary
